lmn/__init__.py
lmn/_version.py
lmn/cli/__init__.py
lmn/cli/_config_loader.py
lmn/cli/_utils.py
lmn/cli/brun.py
lmn/cli/nv.py
lmn/cli/run.py
lmn/cli/sync.py
lmn/config.py
lmn/const.py
lmn/container/__init__.py
lmn/container/docker.py
lmn/container/singularity.py
lmn/helpers.py
lmn/machine.py
lmn/runner.py
lmn/scheduler/__init__.py
lmn/scheduler/pbs.py
lmn/scheduler/slurm.py
lmn-0.5.0.dist-info/entry_points.txt
lmn-0.5.0.dist-info/WHEEL
lmn-0.5.0.dist-info/METADATA
lmn-0.5.0.dist-info/RECORD
