Metadata-Version: 2.1
Name: lmn
Version: 0.5.0
Summary: LMN: A simple launcher
License: MIT License
Author-email: Takuma Yoneda <takuma-yoneda@users.noreply.github.com>,Takuma Yoneda <takuma.ynd@gmail.com>
Requires-Python: >=3.8
Classifier: License :: OSI Approved :: MIT License
Classifier: Operating System :: MacOS
Classifier: Operating System :: POSIX
Classifier: Operating System :: Unix
Classifier: Programming Language :: Python
Classifier: Programming Language :: Python :: 3.6
Classifier: Programming Language :: Python :: 3.7
Classifier: Programming Language :: Python :: 3.8
Classifier: Programming Language :: Python :: 3.9
Requires-Dist: colorlog
Requires-Dist: docker
Requires-Dist: fabric
Requires-Dist: pydantic>=2.5.2
Requires-Dist: pyjson5
Requires-Dist: python-dotenv
Requires-Dist: python-on-whales>=0.68.0
Requires-Dist: randomname
Requires-Dist: simple_slurm_command
Project-URL: Homepage, https://github.com/takuma-yoneda/lmn
